diagnosticism/__init__.py
diagnosticism/conrep.py
diagnosticism/contingent_reporting.py
diagnosticism/log.py
diagnosticism/logging.py
diagnosticism/program_name.py
diagnosticism/severity.py
diagnosticism/trace.py
diagnosticism/tracing.py
diagnosticism/warning.py
examples/__init__.py
examples/abort_with_trailing_prompt.py
examples/conrep.py
examples/log.py
examples/parse_severity.py
examples/trace.py
examples/warn.py
tests/__init__.py
tests/stub.py
tests/test_conrep.py
tests/test_log.py
tests/test_parse_severity.py
diagnosticism-0.9.0.dist-info/LICENSE
diagnosticism-0.9.0.dist-info/METADATA
diagnosticism-0.9.0.dist-info/WHEEL
diagnosticism-0.9.0.dist-info/top_level.txt
diagnosticism-0.9.0.dist-info/RECORD
