Metadata-Version: 2.1
Name: diagnosticism
Version: 0.9.0
Summary: Basic diagnostic facilities, for Python
Home-page: https://github.com/synesissoftware/diagnosticism.Python
Author: Matt Wilson
Author-email: matthew@synesis.com.au
License: BSD-3-Clause
Keywords: Diagnostic Diagnostics Logging Trace Tracing Stopwatch
Classifier: Intended Audience :: Developers
Classifier: License :: OSI Approved :: BSD License
Classifier: Natural Language :: English
Classifier: Operating System :: OS Independent
Classifier: Programming Language :: Python
Classifier: Programming Language :: Python :: 2
Classifier: Programming Language :: Python :: 3
License-File: LICENSE
